portlock/__init__.py
portlock/portlock.py
portlock-0.0.5.dist-info/LICENSE
portlock-0.0.5.dist-info/METADATA
portlock-0.0.5.dist-info/WHEEL
portlock-0.0.5.dist-info/top_level.txt
portlock-0.0.5.dist-info/RECORD
